mypylogicalprograms/__init__.py
mypylogicalprograms/logical/__init__.py
mypylogicalprograms/logical/armstrongnumber.py
mypylogicalprograms/logical/binarysearch.py
mypylogicalprograms/logical/factorial.py
mypylogicalprograms/logical/fibonacciseries.py
mypylogicalprograms/logical/integertoroman.py
mypylogicalprograms/logical/linearsearch.py
mypylogicalprograms/logical/missingnumber.py
mypylogicalprograms/logical/multiplicationtable.py
mypylogicalprograms/logical/numberdigitcount.py
mypylogicalprograms/logical/numberofisland.py
mypylogicalprograms/logical/numbertoword.py
mypylogicalprograms/logical/parentheses.py
mypylogicalprograms/logical/permutation.py
mypylogicalprograms/logical/permutations.py
mypylogicalprograms/logical/reverseinteger.py
mypylogicalprograms/logical/romantointeger.py
mypylogicalprograms/logical/spiralmatrix.py
mypylogicalprograms/logical/stringnumberevaluation.py
mypylogicalprograms/logical/stringreverseandpalindrome.py
mypylogicalprograms/logical/swaptwonumbers.py
mypylogicalprograms/logical/testjustification.py
mypylogicalprograms/logical/zigzagconvertion.py
mypylogicalprograms/patterns/Pypatterns.py
mypylogicalprograms/patterns/__init__.py
mypylogicalprograms/shift/__init__.py
mypylogicalprograms/shift/leftShift.py
mypylogicalprograms/shift/rightShift.py
mypylogicalprograms-1.1.dist-info/LICENSE.txt
mypylogicalprograms-1.1.dist-info/METADATA
mypylogicalprograms-1.1.dist-info/WHEEL
mypylogicalprograms-1.1.dist-info/top_level.txt
mypylogicalprograms-1.1.dist-info/RECORD
